dpaster/__init__.py
dpaster/__main__.py
dpaster/application.py
thepaster-3.2.2.dist-info/LICENSE
thepaster-3.2.2.dist-info/WHEEL
thepaster-3.2.2.dist-info/METADATA
thepaster-3.2.2.dist-info/RECORD
