Metadata-Version: 2.1
Name: thepaster
Version: 3.2.2
Summary: Command-line client interface for https://dpaste.com/ pastebin
License: MIT
Author: adder46
Author-email: dedmauz69@gmail.com
Requires-Python: >=3.6
Classifier: License :: OSI Approved :: MIT License
Classifier: Programming Language :: Python :: 3
Classifier: Programming Language :: Python :: 3.6
Classifier: Programming Language :: Python :: 3.7
Classifier: Programming Language :: Python :: 3.8
Classifier: Programming Language :: Python :: 3.9
Requires-Dist: Pygments (>=2.7.2,<3.0.0)
Requires-Dist: click (>=7.1.2,<8.0.0)
Requires-Dist: click-aliases (>=1.0.1,<2.0.0)
Requires-Dist: pyperclip (>=1.8.1,<2.0.0)
Requires-Dist: requests (>=2.25.0,<3.0.0)
